photo_sorter/__init__.py
photo_sorter-0.1.1.data/scripts/check-complete
photo_sorter-0.1.1.data/scripts/find-duplicates
photo_sorter-0.1.1.data/scripts/photosorter
test/__init__.py
photo_sorter-0.1.1.dist-info/LICENSE
photo_sorter-0.1.1.dist-info/METADATA
photo_sorter-0.1.1.dist-info/WHEEL
photo_sorter-0.1.1.dist-info/top_level.txt
photo_sorter-0.1.1.dist-info/RECORD
