Metadata-Version: 2.1
Name: photo-sorter
Version: 0.1.1
Summary: A collection of scripts used for managing photos
Home-page: https://gitlab.namibsun.net/namibsun/python/photo-sorter
Author: Hermann Krumrey
Author-email: hermann@krumreyh.com
License: GNU GPL3
Platform: UNKNOWN
Classifier: License :: OSI Approved :: GNU General Public License v3 (GPLv3)
Requires-Dist: exifread
Requires-Dist: Pillow
Requires-Dist: colorama
